{
    "1871610400506698761": {
        "result": {
            "ela_distr_skewness": 1.665099,
            "ela_distr_kurtosis": 3.663309,
            "ela_distr_number_of_peaks": 2.0,
            "ela_distr_costs_runtime": 0.078686,
            "ela_level_mmce_lda_10": 0.1,
            "ela_level_mmce_qda_10": 0.1,
            "ela_level_lda_qda_10": 1.0,
            "ela_level_mmce_lda_25": 0.25,
            "ela_level_mmce_qda_25": 0.25,
            "ela_level_lda_qda_25": 1.0,
            "ela_level_mmce_lda_50": 0.46,
            "ela_level_mmce_qda_50": 0.4,
            "ela_level_lda_qda_50": 1.133547,
            "ela_level_costs_runtime": 0.14817,
            "ela_meta_lin_simple_adj_r2": 0.006061,
            "ela_meta_lin_simple_intercept": 54.797249,
            "ela_meta_lin_simple_coef_min": 0.13951,
            "ela_meta_lin_simple_coef_max": 0.516202,
            "ela_meta_lin_simple_coef_max_by_min": 2.637318,
            "ela_meta_lin_w_interact_adj_r2": 0.08457,
            "ela_meta_quad_simple_adj_r2": 0.199918,
            "ela_meta_quad_simple_cond": 2.170822,
            "ela_meta_quad_w_interact_adj_r2": 0.352421,
            "ela_meta_costs_runtime": 0.007628,
            "disp_ratio_mean_02": 0.249517,
            "disp_ratio_mean_05": 0.834543,
            "disp_ratio_mean_10": 0.835199,
            "disp_ratio_mean_25": 0.867656,
            "disp_ratio_median_02": 0.254923,
            "disp_ratio_median_05": 0.946754,
            "disp_ratio_median_10": 0.907265,
            "disp_ratio_median_25": 0.90208,
            "disp_diff_mean_02": -3.936148,
            "disp_diff_mean_05": -0.87094,
            "disp_diff_mean_10": -0.866015,
            "disp_diff_mean_25": -0.694786,
            "disp_diff_median_02": -3.810613,
            "disp_diff_median_05": -0.273011,
            "disp_diff_median_10": -0.481192,
            "disp_diff_median_25": -0.50353,
            "disp_costs_runtime": 0.001761,
            "nbc_nn_nb_sd_ratio": 0.328401,
            "nbc_nn_nb_mean_ratio": 0.585736,
            "nbc_nn_nb_cor": 0.265801,
            "nbc_dist_ratio_coeff_var": 0.402033,
            "nbc_nb_fitness_cor": -0.465018,
            "nbc_costs_runtime": 0.02189,
            "pca_expl_var_cov_x": 1.0,
            "pca_expl_var_cor_x": 1.0,
            "pca_expl_var_cov_init": 0.666667,
            "pca_expl_var_cor_init": 1.0,
            "pca_expl_var_PC1_cov_x": 0.530715,
            "pca_expl_var_PC1_cor_x": 0.5307,
            "pca_expl_var_PC1_cov_init": 0.873829,
            "pca_expl_var_PC1_cor_init": 0.395853,
            "pca_costs_runtime": 0.006282,
            "ic_h_max": 0.846417,
            "ic_eps_s": 1.806807,
            "ic_eps_max": 4.223044,
            "ic_eps_ratio": 0.925926,
            "ic_m0": 0.591837,
            "ic_costs_runtime": 0.605754
        },
        "time": 0.963622
    },
    "1845141783951875736": {
        "result": {
            "ela_distr_skewness": 1.790132,
            "ela_distr_kurtosis": 3.951069,
            "ela_distr_number_of_peaks": 2.0,
            "ela_distr_costs_runtime": 0.034442,
            "ela_level_mmce_lda_10": 0.1,
            "ela_level_mmce_qda_10": 0.1,
            "ela_level_lda_qda_10": 1.0,
            "ela_level_mmce_lda_25": 0.26,
            "ela_level_mmce_qda_25": 0.26,
            "ela_level_lda_qda_25": 0.964286,
            "ela_level_mmce_lda_50": 0.39,
            "ela_level_mmce_qda_50": 0.385,
            "ela_level_lda_qda_50": 0.973684,
            "ela_level_costs_runtime": 0.140692,
            "ela_meta_lin_simple_adj_r2": 0.135521,
            "ela_meta_lin_simple_intercept": 12.287434,
            "ela_meta_lin_simple_coef_min": 0.788189,
            "ela_meta_lin_simple_coef_max": 1.218577,
            "ela_meta_lin_simple_coef_max_by_min": 1.42148,
            "ela_meta_lin_w_interact_adj_r2": 0.144512,
            "ela_meta_quad_simple_adj_r2": 0.225694,
            "ela_meta_quad_simple_cond": 1.428863,
            "ela_meta_quad_w_interact_adj_r2": 0.352172,
            "ela_meta_costs_runtime": 0.00764,
            "disp_ratio_mean_02": 0.327145,
            "disp_ratio_mean_05": 0.704527,
            "disp_ratio_mean_10": 0.827515,
            "disp_ratio_mean_25": 0.908814,
            "disp_ratio_median_02": 0.33391,
            "disp_ratio_median_05": 0.695504,
            "disp_ratio_median_10": 0.827365,
            "disp_ratio_median_25": 0.923616,
            "disp_diff_mean_02": -3.528755,
            "disp_diff_mean_05": -1.549267,
            "disp_diff_mean_10": -0.907096,
            "disp_diff_mean_25": -0.480063,
            "disp_diff_median_02": -3.430527,
            "disp_diff_median_05": -1.569445,
            "disp_diff_median_10": -0.897237,
            "disp_diff_median_25": -0.396317,
            "disp_costs_runtime": 0.001758,
            "nbc_nn_nb_sd_ratio": 0.331998,
            "nbc_nn_nb_mean_ratio": 0.574931,
            "nbc_nn_nb_cor": 0.283375,
            "nbc_dist_ratio_coeff_var": 0.41023,
            "nbc_nb_fitness_cor": -0.457293,
            "nbc_costs_runtime": 0.022721,
            "pca_expl_var_cov_x": 1.0,
            "pca_expl_var_cor_x": 1.0,
            "pca_expl_var_cov_init": 0.666667,
            "pca_expl_var_cor_init": 1.0,
            "pca_expl_var_PC1_cov_x": 0.530715,
            "pca_expl_var_PC1_cor_x": 0.5307,
            "pca_expl_var_PC1_cov_init": 0.887018,
            "pca_expl_var_PC1_cor_init": 0.459827,
            "pca_costs_runtime": 0.00624,
            "ic_h_max": 0.839084,
            "ic_eps_s": 1.786787,
            "ic_eps_max": 4.127917,
            "ic_eps_ratio": 0.925926,
            "ic_m0": 0.581633,
            "ic_costs_runtime": 0.522932
        },
        "time": 0.944095
    },
    "776309667097811824": {
        "result": {
            "ela_distr_skewness": 1.397097,
            "ela_distr_kurtosis": 1.940364,
            "ela_distr_number_of_peaks": 2.0,
            "ela_distr_costs_runtime": 0.059024,
            "ela_level_mmce_lda_10": 0.1,
            "ela_level_mmce_qda_10": 0.1,
            "ela_level_lda_qda_10": 1.0,
            "ela_level_mmce_lda_25": 0.25,
            "ela_level_mmce_qda_25": 0.25,
            "ela_level_lda_qda_25": 1.0,
            "ela_level_mmce_lda_50": 0.49,
            "ela_level_mmce_qda_50": 0.44,
            "ela_level_lda_qda_50": 1.10102,
            "ela_level_costs_runtime": 0.16854,
            "ela_meta_lin_simple_adj_r2": 0.054776,
            "ela_meta_lin_simple_intercept": -355.084048,
            "ela_meta_lin_simple_coef_min": 0.60495,
            "ela_meta_lin_simple_coef_max": 0.941751,
            "ela_meta_lin_simple_coef_max_by_min": 1.498307,
            "ela_meta_lin_w_interact_adj_r2": 0.178129,
            "ela_meta_quad_simple_adj_r2": 0.062661,
            "ela_meta_quad_simple_cond": 2.090843,
            "ela_meta_quad_w_interact_adj_r2": 0.238617,
            "ela_meta_costs_runtime": 0.007666,
            "disp_ratio_mean_02": 0.657221,
            "disp_ratio_mean_05": 0.909617,
            "disp_ratio_mean_10": 1.009577,
            "disp_ratio_mean_25": 1.081135,
            "disp_ratio_median_02": 0.669274,
            "disp_ratio_median_05": 0.954461,
            "disp_ratio_median_10": 1.040374,
            "disp_ratio_median_25": 1.121606,
            "disp_diff_mean_02": -1.797877,
            "disp_diff_mean_05": -0.474563,
            "disp_diff_mean_10": 0.050239,
            "disp_diff_mean_25": 0.425452,
            "disp_diff_median_02": -1.697403,
            "disp_diff_median_05": -0.233988,
            "disp_diff_median_10": 0.208571,
            "disp_diff_median_25": 0.632691,
            "disp_costs_runtime": 0.001753,
            "nbc_nn_nb_sd_ratio": 0.296243,
            "nbc_nn_nb_mean_ratio": 0.565458,
            "nbc_nn_nb_cor": 0.27533,
            "nbc_dist_ratio_coeff_var": 0.410921,
            "nbc_nb_fitness_cor": -0.455378,
            "nbc_costs_runtime": 0.022951,
            "pca_expl_var_cov_x": 1.0,
            "pca_expl_var_cor_x": 1.0,
            "pca_expl_var_cov_init": 0.333333,
            "pca_expl_var_cor_init": 1.0,
            "pca_expl_var_PC1_cov_x": 0.530715,
            "pca_expl_var_PC1_cor_x": 0.5307,
            "pca_expl_var_PC1_cov_init": 0.902491,
            "pca_expl_var_PC1_cor_init": 0.431479,
            "pca_costs_runtime": 0.006301,
            "ic_h_max": 0.844191,
            "ic_eps_s": 1.846847,
            "ic_eps_max": 4.422274,
            "ic_eps_ratio": 0.945946,
            "ic_m0": 0.581633,
            "ic_costs_runtime": 0.658516
        },
        "time": 1.163707
    },
    "563806771103299940": {
        "result": {
            "ela_distr_skewness": 1.163952,
            "ela_distr_kurtosis": 1.039808,
            "ela_distr_number_of_peaks": 2.0,
            "ela_distr_costs_runtime": 0.053605,
            "ela_level_mmce_lda_10": 0.1,
            "ela_level_mmce_qda_10": 0.1,
            "ela_level_lda_qda_10": 1.0,
            "ela_level_mmce_lda_25": 0.26,
            "ela_level_mmce_qda_25": 0.26,
            "ela_level_lda_qda_25": 1.0,
            "ela_level_mmce_lda_50": 0.35,
            "ela_level_mmce_qda_50": 0.3,
            "ela_level_lda_qda_50": 1.22408,
            "ela_level_costs_runtime": 0.18791,
            "ela_meta_lin_simple_adj_r2": 0.145312,
            "ela_meta_lin_simple_intercept": -16.468315,
            "ela_meta_lin_simple_coef_min": 0.965316,
            "ela_meta_lin_simple_coef_max": 1.338056,
            "ela_meta_lin_simple_coef_max_by_min": 1.392656,
            "ela_meta_lin_w_interact_adj_r2": 0.171205,
            "ela_meta_quad_simple_adj_r2": 0.346983,
            "ela_meta_quad_simple_cond": 1.252327,
            "ela_meta_quad_w_interact_adj_r2": 0.48566,
            "ela_meta_costs_runtime": 0.007606,
            "disp_ratio_mean_02": 0.795763,
            "disp_ratio_mean_05": 0.845454,
            "disp_ratio_mean_10": 0.820344,
            "disp_ratio_mean_25": 0.804773,
            "disp_ratio_median_02": 0.814049,
            "disp_ratio_median_05": 0.872342,
            "disp_ratio_median_10": 0.859953,
            "disp_ratio_median_25": 0.815468,
            "disp_diff_mean_02": -1.07036,
            "disp_diff_mean_05": -0.812807,
            "disp_diff_mean_10": -0.94285,
            "disp_diff_mean_25": -1.024366,
            "disp_diff_median_02": -0.954677,
            "disp_diff_median_05": -0.659154,
            "disp_diff_median_10": -0.727124,
            "disp_diff_median_25": -0.950499,
            "disp_costs_runtime": 0.001754,
            "nbc_nn_nb_sd_ratio": 0.348324,
            "nbc_nn_nb_mean_ratio": 0.59255,
            "nbc_nn_nb_cor": 0.278747,
            "nbc_dist_ratio_coeff_var": 0.401141,
            "nbc_nb_fitness_cor": -0.455779,
            "nbc_costs_runtime": 0.022222,
            "pca_expl_var_cov_x": 1.0,
            "pca_expl_var_cor_x": 1.0,
            "pca_expl_var_cov_init": 0.333333,
            "pca_expl_var_cor_init": 1.0,
            "pca_expl_var_PC1_cov_x": 0.530715,
            "pca_expl_var_PC1_cor_x": 0.5307,
            "pca_expl_var_PC1_cov_init": 0.911882,
            "pca_expl_var_PC1_cor_init": 0.472135,
            "pca_costs_runtime": 0.006251,
            "ic_h_max": 0.848474,
            "ic_eps_s": 1.846847,
            "ic_eps_max": 4.630903,
            "ic_eps_ratio": 0.945946,
            "ic_m0": 0.591837,
            "ic_costs_runtime": 0.726776
        },
        "time": 1.103074
    },
    "112974639736012942": {
        "result": {
            "ela_distr_skewness": 1.769214,
            "ela_distr_kurtosis": 4.092687,
            "ela_distr_number_of_peaks": 2.0,
            "ela_distr_costs_runtime": 0.056034,
            "ela_level_mmce_lda_10": 0.1,
            "ela_level_mmce_qda_10": 0.1,
            "ela_level_lda_qda_10": 1.0,
            "ela_level_mmce_lda_25": 0.25,
            "ela_level_mmce_qda_25": 0.25,
            "ela_level_lda_qda_25": 1.0,
            "ela_level_mmce_lda_50": 0.455,
            "ela_level_mmce_qda_50": 0.485,
            "ela_level_lda_qda_50": 0.961774,
            "ela_level_costs_runtime": 0.161853,
            "ela_meta_lin_simple_adj_r2": 0.03218,
            "ela_meta_lin_simple_intercept": 530.144767,
            "ela_meta_lin_simple_coef_min": 0.371666,
            "ela_meta_lin_simple_coef_max": 0.791258,
            "ela_meta_lin_simple_coef_max_by_min": 1.90533,
            "ela_meta_lin_w_interact_adj_r2": 0.036055,
            "ela_meta_quad_simple_adj_r2": 0.051584,
            "ela_meta_quad_simple_cond": 2.130735,
            "ela_meta_quad_w_interact_adj_r2": 0.150071,
            "ela_meta_costs_runtime": 0.007713,
            "disp_ratio_mean_02": 0.235302,
            "disp_ratio_mean_05": 1.016445,
            "disp_ratio_mean_10": 1.022902,
            "disp_ratio_mean_25": 1.00523,
            "disp_ratio_median_02": 0.238019,
            "disp_ratio_median_05": 1.056051,
            "disp_ratio_median_10": 1.079959,
            "disp_ratio_median_25": 1.048907,
            "disp_diff_mean_02": -4.026145,
            "disp_diff_mean_05": 0.086549,
            "disp_diff_mean_10": 0.120298,
            "disp_diff_mean_25": 0.027408,
            "disp_diff_median_02": -3.968359,
            "disp_diff_median_05": 0.289478,
            "disp_diff_median_10": 0.413844,
            "disp_diff_median_25": 0.253924,
            "disp_costs_runtime": 0.001762,
            "nbc_nn_nb_sd_ratio": 0.270407,
            "nbc_nn_nb_mean_ratio": 0.555262,
            "nbc_nn_nb_cor": 0.257962,
            "nbc_dist_ratio_coeff_var": 0.412946,
            "nbc_nb_fitness_cor": -0.478081,
            "nbc_costs_runtime": 0.023385,
            "pca_expl_var_cov_x": 1.0,
            "pca_expl_var_cor_x": 1.0,
            "pca_expl_var_cov_init": 0.666667,
            "pca_expl_var_cor_init": 1.0,
            "pca_expl_var_PC1_cov_x": 0.530715,
            "pca_expl_var_PC1_cor_x": 0.5307,
            "pca_expl_var_PC1_cov_init": 0.889753,
            "pca_expl_var_PC1_cor_init": 0.422181,
            "pca_costs_runtime": 0.006358,
            "ic_h_max": 0.843002,
            "ic_eps_s": 1.866867,
            "ic_eps_max": 4.849374,
            "ic_eps_ratio": 0.965966,
            "ic_m0": 0.591837,
            "ic_costs_runtime": 0.606325
        },
        "time": 1.056709
    },
    "2194583684859627522": {
        "result": {
            "ela_distr_skewness": 0.542269,
            "ela_distr_kurtosis": -0.69775,
            "ela_distr_number_of_peaks": 1.0,
            "ela_distr_costs_runtime": 0.075345,
            "ela_level_mmce_lda_10": 0.1,
            "ela_level_mmce_qda_10": 0.1,
            "ela_level_lda_qda_10": 1.0,
            "ela_level_mmce_lda_25": 0.253333,
            "ela_level_mmce_qda_25": 0.256667,
            "ela_level_lda_qda_25": 1.0,
            "ela_level_mmce_lda_50": 0.46,
            "ela_level_mmce_qda_50": 0.416667,
            "ela_level_lda_qda_50": 1.138095,
            "ela_level_costs_runtime": 0.16279,
            "ela_meta_lin_simple_adj_r2": 0.040529,
            "ela_meta_lin_simple_intercept": 72.28126,
            "ela_meta_lin_simple_coef_min": 0.323446,
            "ela_meta_lin_simple_coef_max": 1.272491,
            "ela_meta_lin_simple_coef_max_by_min": 3.849684,
            "ela_meta_lin_w_interact_adj_r2": 0.058831,
            "ela_meta_quad_simple_adj_r2": 0.203048,
            "ela_meta_quad_simple_cond": 2.044167,
            "ela_meta_quad_w_interact_adj_r2": 0.321879,
            "ela_meta_costs_runtime": 0.008037,
            "disp_ratio_mean_02": 0.836565,
            "disp_ratio_mean_05": 0.837103,
            "disp_ratio_mean_10": 0.859269,
            "disp_ratio_mean_25": 0.899224,
            "disp_ratio_median_02": 0.858512,
            "disp_ratio_median_05": 0.821975,
            "disp_ratio_median_10": 0.864095,
            "disp_ratio_median_25": 0.898308,
            "disp_diff_mean_02": -1.086028,
            "disp_diff_mean_05": -1.081851,
            "disp_diff_mean_10": -0.935902,
            "disp_diff_mean_25": -0.670885,
            "disp_diff_median_02": -0.943833,
            "disp_diff_median_05": -1.183926,
            "disp_diff_median_10": -0.908709,
            "disp_diff_median_25": -0.677141,
            "disp_costs_runtime": 0.002194,
            "nbc_nn_nb_sd_ratio": 0.455844,
            "nbc_nn_nb_mean_ratio": 0.700486,
            "nbc_nn_nb_cor": 0.343895,
            "nbc_dist_ratio_coeff_var": 0.325726,
            "nbc_nb_fitness_cor": -0.544264,
            "nbc_costs_runtime": 0.02364,
            "pca_expl_var_cov_x": 1.0,
            "pca_expl_var_cor_x": 1.0,
            "pca_expl_var_cov_init": 0.25,
            "pca_expl_var_cor_init": 1.0,
            "pca_expl_var_PC1_cov_x": 0.378394,
            "pca_expl_var_PC1_cor_x": 0.378412,
            "pca_expl_var_PC1_cov_init": 0.93408,
            "pca_expl_var_PC1_cor_init": 0.316338,
            "pca_costs_runtime": 0.006469,
            "ic_h_max": 0.859257,
            "ic_eps_s": 1.626627,
            "ic_eps_max": 5.568596,
            "ic_eps_ratio": 0.985986,
            "ic_m0": 0.594595,
            "ic_costs_runtime": 0.937076
        },
        "time": 1.384723
    },
    "1608823368663021363": {
        "result": {
            "ela_distr_skewness": 0.452075,
            "ela_distr_kurtosis": -0.880255,
            "ela_distr_number_of_peaks": 1.0,
            "ela_distr_costs_runtime": 0.054846,
            "ela_level_mmce_lda_10": 0.1,
            "ela_level_mmce_qda_10": 0.1,
            "ela_level_lda_qda_10": 1.0,
            "ela_level_mmce_lda_25": 0.26,
            "ela_level_mmce_qda_25": 0.266667,
            "ela_level_lda_qda_25": 0.974359,
            "ela_level_mmce_lda_50": 0.42,
            "ela_level_mmce_qda_50": 0.35,
            "ela_level_lda_qda_50": 1.192982,
            "ela_level_costs_runtime": 0.162762,
            "ela_meta_lin_simple_adj_r2": 0.065295,
            "ela_meta_lin_simple_intercept": 29.839326,
            "ela_meta_lin_simple_coef_min": 0.279319,
            "ela_meta_lin_simple_coef_max": 1.594873,
            "ela_meta_lin_simple_coef_max_by_min": 6.184479,
            "ela_meta_lin_w_interact_adj_r2": 0.131146,
            "ela_meta_quad_simple_adj_r2": 0.178926,
            "ela_meta_quad_simple_cond": 3.917856,
            "ela_meta_quad_w_interact_adj_r2": 0.387139,
            "ela_meta_costs_runtime": 0.007873,
            "disp_ratio_mean_02": 0.756279,
            "disp_ratio_mean_05": 0.801058,
            "disp_ratio_mean_10": 0.824752,
            "disp_ratio_mean_25": 0.877056,
            "disp_ratio_median_02": 0.755193,
            "disp_ratio_median_05": 0.80338,
            "disp_ratio_median_10": 0.805097,
            "disp_ratio_median_25": 0.855839,
            "disp_diff_mean_02": -1.619935,
            "disp_diff_mean_05": -1.3225,
            "disp_diff_mean_10": -1.164867,
            "disp_diff_mean_25": -0.817305,
            "disp_diff_median_02": -1.635266,
            "disp_diff_median_05": -1.301993,
            "disp_diff_median_10": -1.291147,
            "disp_diff_median_25": -0.959118,
            "disp_costs_runtime": 0.002166,
            "nbc_nn_nb_sd_ratio": 0.455319,
            "nbc_nn_nb_mean_ratio": 0.708056,
            "nbc_nn_nb_cor": 0.338866,
            "nbc_dist_ratio_coeff_var": 0.32039,
            "nbc_nb_fitness_cor": -0.520903,
            "nbc_costs_runtime": 0.022488,
            "pca_expl_var_cov_x": 1.0,
            "pca_expl_var_cor_x": 1.0,
            "pca_expl_var_cov_init": 0.25,
            "pca_expl_var_cor_init": 1.0,
            "pca_expl_var_PC1_cov_x": 0.378394,
            "pca_expl_var_PC1_cor_x": 0.378412,
            "pca_expl_var_PC1_cov_init": 0.936192,
            "pca_expl_var_PC1_cor_init": 0.329042,
            "pca_costs_runtime": 0.006306,
            "ic_h_max": 0.86046,
            "ic_eps_s": 1.626627,
            "ic_eps_max": 5.25783,
            "ic_eps_ratio": 0.965966,
            "ic_m0": 0.601351,
            "ic_costs_runtime": 0.811692
        },
        "time": 1.242949
    },
    "1629030988204244671": {
        "result": {
            "ela_distr_skewness": 0.549289,
            "ela_distr_kurtosis": -0.532863,
            "ela_distr_number_of_peaks": 1.0,
            "ela_distr_costs_runtime": 0.042622,
            "ela_level_mmce_lda_10": 0.1,
            "ela_level_mmce_qda_10": 0.1,
            "ela_level_lda_qda_10": 1.0,
            "ela_level_mmce_lda_25": 0.253333,
            "ela_level_mmce_qda_25": 0.26,
            "ela_level_lda_qda_25": 0.974359,
            "ela_level_mmce_lda_50": 0.453333,
            "ela_level_mmce_qda_50": 0.436667,
            "ela_level_lda_qda_50": 1.056763,
            "ela_level_costs_runtime": 0.15233,
            "ela_meta_lin_simple_adj_r2": 0.033545,
            "ela_meta_lin_simple_intercept": -340.547781,
            "ela_meta_lin_simple_coef_min": 0.396454,
            "ela_meta_lin_simple_coef_max": 1.071447,
            "ela_meta_lin_simple_coef_max_by_min": 3.139937,
            "ela_meta_lin_w_interact_adj_r2": 0.05032,
            "ela_meta_quad_simple_adj_r2": 0.084992,
            "ela_meta_quad_simple_cond": 3.453726,
            "ela_meta_quad_w_interact_adj_r2": 0.196241,
            "ela_meta_costs_runtime": 0.007832,
            "disp_ratio_mean_02": 0.973812,
            "disp_ratio_mean_05": 0.972476,
            "disp_ratio_mean_10": 0.960852,
            "disp_ratio_mean_25": 0.959253,
            "disp_ratio_median_02": 1.067098,
            "disp_ratio_median_05": 0.995861,
            "disp_ratio_median_10": 0.979424,
            "disp_ratio_median_25": 0.969827,
            "disp_diff_mean_02": -0.173874,
            "disp_diff_mean_05": -0.183152,
            "disp_diff_mean_10": -0.260435,
            "disp_diff_mean_25": -0.270501,
            "disp_diff_median_02": 0.447,
            "disp_diff_median_05": -0.027416,
            "disp_diff_median_10": -0.13619,
            "disp_diff_median_25": -0.2009,
            "disp_costs_runtime": 0.002167,
            "nbc_nn_nb_sd_ratio": 0.404276,
            "nbc_nn_nb_mean_ratio": 0.688538,
            "nbc_nn_nb_cor": 0.336466,
            "nbc_dist_ratio_coeff_var": 0.33048,
            "nbc_nb_fitness_cor": -0.554964,
            "nbc_costs_runtime": 0.02422,
            "pca_expl_var_cov_x": 1.0,
            "pca_expl_var_cor_x": 1.0,
            "pca_expl_var_cov_init": 0.25,
            "pca_expl_var_cor_init": 1.0,
            "pca_expl_var_PC1_cov_x": 0.378394,
            "pca_expl_var_PC1_cor_x": 0.378412,
            "pca_expl_var_PC1_cov_init": 0.922091,
            "pca_expl_var_PC1_cor_init": 0.315022,
            "pca_costs_runtime": 0.006346,
            "ic_h_max": 0.867647,
            "ic_eps_s": 1.626627,
            "ic_eps_max": 5.317723,
            "ic_eps_ratio": 0.985986,
            "ic_m0": 0.60473,
            "ic_costs_runtime": 1.059718
        },
        "time": 1.541648
    },
    "1363844144595046529": {
        "result": {
            "ela_distr_skewness": 0.371365,
            "ela_distr_kurtosis": -0.874997,
            "ela_distr_number_of_peaks": 1.0,
            "ela_distr_costs_runtime": 0.030511,
            "ela_level_mmce_lda_10": 0.1,
            "ela_level_mmce_qda_10": 0.1,
            "ela_level_lda_qda_10": 1.0,
            "ela_level_mmce_lda_25": 0.253333,
            "ela_level_mmce_qda_25": 0.26,
            "ela_level_lda_qda_25": 0.974359,
            "ela_level_mmce_lda_50": 0.48,
            "ela_level_mmce_qda_50": 0.436667,
            "ela_level_lda_qda_50": 1.078201,
            "ela_level_costs_runtime": 0.221283,
            "ela_meta_lin_simple_adj_r2": 0.022549,
            "ela_meta_lin_simple_intercept": 0.454015,
            "ela_meta_lin_simple_coef_min": 0.219339,
            "ela_meta_lin_simple_coef_max": 1.091942,
            "ela_meta_lin_simple_coef_max_by_min": 5.045781,
            "ela_meta_lin_w_interact_adj_r2": 0.099507,
            "ela_meta_quad_simple_adj_r2": 0.025569,
            "ela_meta_quad_simple_cond": 5.24337,
            "ela_meta_quad_w_interact_adj_r2": 0.202805,
            "ela_meta_costs_runtime": 0.008015,
            "disp_ratio_mean_02": 1.029085,
            "disp_ratio_mean_05": 1.0403,
            "disp_ratio_mean_10": 1.035139,
            "disp_ratio_mean_25": 0.994498,
            "disp_ratio_median_02": 1.095748,
            "disp_ratio_median_05": 1.012575,
            "disp_ratio_median_10": 1.052156,
            "disp_ratio_median_25": 1.004009,
            "disp_diff_mean_02": 0.19321,
            "disp_diff_mean_05": 0.268118,
            "disp_diff_mean_10": 0.233732,
            "disp_diff_mean_25": -0.03661,
            "disp_diff_median_02": 0.640668,
            "disp_diff_median_05": 0.083782,
            "disp_diff_median_10": 0.346342,
            "disp_diff_median_25": 0.026718,
            "disp_costs_runtime": 0.0022,
            "nbc_nn_nb_sd_ratio": 0.375257,
            "nbc_nn_nb_mean_ratio": 0.68643,
            "nbc_nn_nb_cor": 0.30808,
            "nbc_dist_ratio_coeff_var": 0.331071,
            "nbc_nb_fitness_cor": -0.554405,
            "nbc_costs_runtime": 0.025738,
            "pca_expl_var_cov_x": 1.0,
            "pca_expl_var_cor_x": 1.0,
            "pca_expl_var_cov_init": 0.25,
            "pca_expl_var_cor_init": 1.0,
            "pca_expl_var_PC1_cov_x": 0.378394,
            "pca_expl_var_PC1_cor_x": 0.378412,
            "pca_expl_var_PC1_cov_init": 0.930063,
            "pca_expl_var_PC1_cor_init": 0.311504,
            "pca_costs_runtime": 0.006446,
            "ic_h_max": 0.869265,
            "ic_eps_s": 1.646647,
            "ic_eps_max": 5.568596,
            "ic_eps_ratio": 1.006006,
            "ic_m0": 0.614865,
            "ic_costs_runtime": 0.854996
        },
        "time": 1.306689
    },
    "512686388532353428": {
        "result": {
            "ela_distr_skewness": 0.462409,
            "ela_distr_kurtosis": -0.787572,
            "ela_distr_number_of_peaks": 1.0,
            "ela_distr_costs_runtime": 0.058453,
            "ela_level_mmce_lda_10": 0.1,
            "ela_level_mmce_qda_10": 0.1,
            "ela_level_lda_qda_10": 1.0,
            "ela_level_mmce_lda_25": 0.253333,
            "ela_level_mmce_qda_25": 0.26,
            "ela_level_lda_qda_25": 0.974359,
            "ela_level_mmce_lda_50": 0.5,
            "ela_level_mmce_qda_50": 0.46,
            "ela_level_lda_qda_50": 1.089572,
            "ela_level_costs_runtime": 0.15167,
            "ela_meta_lin_simple_adj_r2": 0.005805,
            "ela_meta_lin_simple_intercept": 547.590764,
            "ela_meta_lin_simple_coef_min": 0.100903,
            "ela_meta_lin_simple_coef_max": 0.889289,
            "ela_meta_lin_simple_coef_max_by_min": 6.52765,
            "ela_meta_lin_w_interact_adj_r2": 0.005451,
            "ela_meta_quad_simple_adj_r2": 0.071316,
            "ela_meta_quad_simple_cond": 4.889793,
            "ela_meta_quad_w_interact_adj_r2": 0.228346,
            "ela_meta_costs_runtime": 0.007852,
            "disp_ratio_mean_02": 0.867964,
            "disp_ratio_mean_05": 0.871228,
            "disp_ratio_mean_10": 0.909289,
            "disp_ratio_mean_25": 0.93552,
            "disp_ratio_median_02": 0.908306,
            "disp_ratio_median_05": 0.89109,
            "disp_ratio_median_10": 0.922664,
            "disp_ratio_median_25": 0.932965,
            "disp_diff_mean_02": -0.877906,
            "disp_diff_mean_05": -0.855876,
            "disp_diff_mean_10": -0.602968,
            "disp_diff_mean_25": -0.427932,
            "disp_diff_median_02": -0.608489,
            "disp_diff_median_05": -0.723809,
            "disp_diff_median_10": -0.511342,
            "disp_diff_median_25": -0.445472,
            "disp_costs_runtime": 0.002184,
            "nbc_nn_nb_sd_ratio": 0.418687,
            "nbc_nn_nb_mean_ratio": 0.692763,
            "nbc_nn_nb_cor": 0.347186,
            "nbc_dist_ratio_coeff_var": 0.327862,
            "nbc_nb_fitness_cor": -0.552292,
            "nbc_costs_runtime": 0.024552,
            "pca_expl_var_cov_x": 1.0,
            "pca_expl_var_cor_x": 1.0,
            "pca_expl_var_cov_init": 0.25,
            "pca_expl_var_cor_init": 1.0,
            "pca_expl_var_PC1_cov_x": 0.378394,
            "pca_expl_var_PC1_cor_x": 0.378412,
            "pca_expl_var_PC1_cov_init": 0.930648,
            "pca_expl_var_PC1_cor_init": 0.295784,
            "pca_costs_runtime": 0.006331,
            "ic_h_max": 0.863887,
            "ic_eps_s": 1.666667,
            "ic_eps_max": 5.317723,
            "ic_eps_ratio": 1.026026,
            "ic_m0": 0.601351,
            "ic_costs_runtime": 0.781712
        },
        "time": 1.179331
    },
    "1147805612484424091": {
        "result": {
            "ela_distr_skewness": -1.186192,
            "ela_distr_kurtosis": 0.731818,
            "ela_distr_number_of_peaks": 1.0,
            "ela_distr_costs_runtime": 0.040446,
            "ela_level_mmce_lda_10": 0.1,
            "ela_level_mmce_qda_10": 0.104,
            "ela_level_lda_qda_10": 0.961538,
            "ela_level_mmce_lda_25": 0.256,
            "ela_level_mmce_qda_25": 0.256,
            "ela_level_lda_qda_25": 0.992424,
            "ela_level_mmce_lda_50": 0.436,
            "ela_level_mmce_qda_50": 0.398,
            "ela_level_lda_qda_50": 1.098544,
            "ela_level_costs_runtime": 0.146448,
            "ela_meta_lin_simple_adj_r2": 0.038066,
            "ela_meta_lin_simple_intercept": 101.652458,
            "ela_meta_lin_simple_coef_min": 0.174768,
            "ela_meta_lin_simple_coef_max": 0.883322,
            "ela_meta_lin_simple_coef_max_by_min": 4.519226,
            "ela_meta_lin_w_interact_adj_r2": 0.084699,
            "ela_meta_quad_simple_adj_r2": 0.098836,
            "ela_meta_quad_simple_cond": 4.950831,
            "ela_meta_quad_w_interact_adj_r2": 0.226287,
            "ela_meta_costs_runtime": 0.326324,
            "disp_ratio_mean_02": 0.899605,
            "disp_ratio_mean_05": 0.934884,
            "disp_ratio_mean_10": 0.935768,
            "disp_ratio_mean_25": 0.936644,
            "disp_ratio_median_02": 0.963125,
            "disp_ratio_median_05": 0.941959,
            "disp_ratio_median_10": 0.937787,
            "disp_ratio_median_25": 0.939297,
            "disp_diff_mean_02": -0.883477,
            "disp_diff_mean_05": -0.574044,
            "disp_diff_mean_10": -0.566083,
            "disp_diff_mean_25": -0.55731,
            "disp_diff_median_02": -0.325822,
            "disp_diff_median_05": -0.512082,
            "disp_diff_median_10": -0.55151,
            "disp_diff_median_25": -0.536331,
            "disp_costs_runtime": 0.00376,
            "nbc_nn_nb_sd_ratio": 0.562634,
            "nbc_nn_nb_mean_ratio": 0.809079,
            "nbc_nn_nb_cor": 0.423239,
            "nbc_dist_ratio_coeff_var": 0.234924,
            "nbc_nb_fitness_cor": -0.634087,
            "nbc_costs_runtime": 0.028412,
            "pca_expl_var_cov_x": 1.0,
            "pca_expl_var_cor_x": 1.0,
            "pca_expl_var_cov_init": 0.5,
            "pca_expl_var_cor_init": 1.0,
            "pca_expl_var_PC1_cov_x": 0.237642,
            "pca_expl_var_PC1_cor_x": 0.237647,
            "pca_expl_var_PC1_cov_init": 0.868535,
            "pca_expl_var_PC1_cor_init": 0.212132,
            "pca_costs_runtime": 0.006547,
            "ic_h_max": 0.833021,
            "ic_eps_s": 1.326326,
            "ic_eps_max": 1.679675,
            "ic_eps_ratio": 0.605606,
            "ic_m0": 0.608871,
            "ic_costs_runtime": 1.617072
        },
        "time": 2.459843
    },
    "302932566726882240": {
        "result": {
            "ela_distr_skewness": -1.107688,
            "ela_distr_kurtosis": 0.392744,
            "ela_distr_number_of_peaks": 2.0,
            "ela_distr_costs_runtime": 0.035494,
            "ela_level_mmce_lda_10": 0.1,
            "ela_level_mmce_qda_10": 0.104,
            "ela_level_lda_qda_10": 0.961538,
            "ela_level_mmce_lda_25": 0.256,
            "ela_level_mmce_qda_25": 0.264,
            "ela_level_lda_qda_25": 0.969697,
            "ela_level_mmce_lda_50": 0.452,
            "ela_level_mmce_qda_50": 0.424,
            "ela_level_lda_qda_50": 1.088933,
            "ela_level_costs_runtime": 0.1457,
            "ela_meta_lin_simple_adj_r2": 0.024611,
            "ela_meta_lin_simple_intercept": 57.794482,
            "ela_meta_lin_simple_coef_min": 0.092818,
            "ela_meta_lin_simple_coef_max": 0.887882,
            "ela_meta_lin_simple_coef_max_by_min": 9.784681,
            "ela_meta_lin_w_interact_adj_r2": 0.067671,
            "ela_meta_quad_simple_adj_r2": 0.068479,
            "ela_meta_quad_simple_cond": 4.417372,
            "ela_meta_quad_w_interact_adj_r2": 0.201546,
            "ela_meta_costs_runtime": 0.409858,
            "disp_ratio_mean_02": 0.930758,
            "disp_ratio_mean_05": 0.92885,
            "disp_ratio_mean_10": 0.935207,
            "disp_ratio_mean_25": 0.933849,
            "disp_ratio_median_02": 0.901061,
            "disp_ratio_median_05": 0.928535,
            "disp_ratio_median_10": 0.937078,
            "disp_ratio_median_25": 0.931561,
            "disp_diff_mean_02": -0.609445,
            "disp_diff_mean_05": -0.625855,
            "disp_diff_mean_10": -0.570845,
            "disp_diff_mean_25": -0.582049,
            "disp_diff_median_02": -0.876088,
            "disp_diff_median_05": -0.633367,
            "disp_diff_median_10": -0.558738,
            "disp_diff_median_25": -0.603436,
            "disp_costs_runtime": 0.003719,
            "nbc_nn_nb_sd_ratio": 0.566922,
            "nbc_nn_nb_mean_ratio": 0.808562,
            "nbc_nn_nb_cor": 0.420015,
            "nbc_dist_ratio_coeff_var": 0.233915,
            "nbc_nb_fitness_cor": -0.642751,
            "nbc_costs_runtime": 0.029218,
            "pca_expl_var_cov_x": 1.0,
            "pca_expl_var_cor_x": 1.0,
            "pca_expl_var_cov_init": 0.333333,
            "pca_expl_var_cor_init": 1.0,
            "pca_expl_var_PC1_cov_x": 0.237642,
            "pca_expl_var_PC1_cor_x": 0.237647,
            "pca_expl_var_PC1_cov_init": 0.870456,
            "pca_expl_var_PC1_cor_init": 0.20954,
            "pca_costs_runtime": 0.006634,
            "ic_h_max": 0.833451,
            "ic_eps_s": 1.336336,
            "ic_eps_max": 1.841897,
            "ic_eps_ratio": 0.645646,
            "ic_m0": 0.608871,
            "ic_costs_runtime": 1.793888
        },
        "time": 2.598028
    },
    "150358351380387796": {
        "result": {
            "ela_distr_skewness": -1.142054,
            "ela_distr_kurtosis": 0.518812,
            "ela_distr_number_of_peaks": 1.0,
            "ela_distr_costs_runtime": 0.039051,
            "ela_level_mmce_lda_10": 0.1,
            "ela_level_mmce_qda_10": 0.104,
            "ela_level_lda_qda_10": 0.961538,
            "ela_level_mmce_lda_25": 0.254,
            "ela_level_mmce_qda_25": 0.268,
            "ela_level_lda_qda_25": 0.955224,
            "ela_level_mmce_lda_50": 0.446,
            "ela_level_mmce_qda_50": 0.42,
            "ela_level_lda_qda_50": 1.056624,
            "ela_level_costs_runtime": 0.147043,
            "ela_meta_lin_simple_adj_r2": 0.026081,
            "ela_meta_lin_simple_intercept": -311.452175,
            "ela_meta_lin_simple_coef_min": 0.112243,
            "ela_meta_lin_simple_coef_max": 0.896414,
            "ela_meta_lin_simple_coef_max_by_min": 7.582753,
            "ela_meta_lin_w_interact_adj_r2": 0.063401,
            "ela_meta_quad_simple_adj_r2": 0.049608,
            "ela_meta_quad_simple_cond": 8.965368,
            "ela_meta_quad_w_interact_adj_r2": 0.159198,
            "ela_meta_costs_runtime": 0.225787,
            "disp_ratio_mean_02": 0.944193,
            "disp_ratio_mean_05": 0.966449,
            "disp_ratio_mean_10": 0.967709,
            "disp_ratio_mean_25": 0.965841,
            "disp_ratio_median_02": 0.947715,
            "disp_ratio_median_05": 0.959965,
            "disp_ratio_median_10": 0.968066,
            "disp_ratio_median_25": 0.971345,
            "disp_diff_mean_02": -0.491357,
            "disp_diff_mean_05": -0.295491,
            "disp_diff_mean_10": -0.284345,
            "disp_diff_mean_25": -0.300846,
            "disp_diff_median_02": -0.46156,
            "disp_diff_median_05": -0.353911,
            "disp_diff_median_10": -0.282663,
            "disp_diff_median_25": -0.25363,
            "disp_costs_runtime": 0.003641,
            "nbc_nn_nb_sd_ratio": 0.545832,
            "nbc_nn_nb_mean_ratio": 0.801319,
            "nbc_nn_nb_cor": 0.405795,
            "nbc_dist_ratio_coeff_var": 0.239954,
            "nbc_nb_fitness_cor": -0.635192,
            "nbc_costs_runtime": 0.031492,
            "pca_expl_var_cov_x": 1.0,
            "pca_expl_var_cor_x": 1.0,
            "pca_expl_var_cov_init": 0.333333,
            "pca_expl_var_cor_init": 1.0,
            "pca_expl_var_PC1_cov_x": 0.237642,
            "pca_expl_var_PC1_cor_x": 0.237647,
            "pca_expl_var_PC1_cov_init": 0.870753,
            "pca_expl_var_PC1_cor_init": 0.208216,
            "pca_costs_runtime": 0.00663,
            "ic_h_max": 0.829225,
            "ic_eps_s": 1.326326,
            "ic_eps_max": 1.800407,
            "ic_eps_ratio": 0.625626,
            "ic_m0": 0.633065,
            "ic_costs_runtime": 1.614233
        },
        "time": 2.328041
    },
    "88326999597976630": {
        "result": {
            "ela_distr_skewness": -1.234094,
            "ela_distr_kurtosis": 0.829838,
            "ela_distr_number_of_peaks": 1.0,
            "ela_distr_costs_runtime": 0.027284,
            "ela_level_mmce_lda_10": 0.1,
            "ela_level_mmce_qda_10": 0.104,
            "ela_level_lda_qda_10": 0.961538,
            "ela_level_mmce_lda_25": 0.252,
            "ela_level_mmce_qda_25": 0.27,
            "ela_level_lda_qda_25": 0.941164,
            "ela_level_mmce_lda_50": 0.458,
            "ela_level_mmce_qda_50": 0.396,
            "ela_level_lda_qda_50": 1.139931,
            "ela_level_costs_runtime": 0.163333,
            "ela_meta_lin_simple_adj_r2": 0.014011,
            "ela_meta_lin_simple_intercept": 28.027287,
            "ela_meta_lin_simple_coef_min": 0.111691,
            "ela_meta_lin_simple_coef_max": 0.790471,
            "ela_meta_lin_simple_coef_max_by_min": 6.349516,
            "ela_meta_lin_w_interact_adj_r2": 0.085705,
            "ela_meta_quad_simple_adj_r2": 0.055014,
            "ela_meta_quad_simple_cond": 5.809842,
            "ela_meta_quad_w_interact_adj_r2": 0.210985,
            "ela_meta_costs_runtime": 0.307632,
            "disp_ratio_mean_02": 0.94348,
            "disp_ratio_mean_05": 0.947944,
            "disp_ratio_mean_10": 0.960065,
            "disp_ratio_mean_25": 0.95597,
            "disp_ratio_median_02": 0.973097,
            "disp_ratio_median_05": 0.952763,
            "disp_ratio_median_10": 0.960518,
            "disp_ratio_median_25": 0.958725,
            "disp_diff_mean_02": -0.497496,
            "disp_diff_mean_05": -0.458527,
            "disp_diff_mean_10": -0.351904,
            "disp_diff_mean_25": -0.387422,
            "disp_diff_median_02": -0.237733,
            "disp_diff_median_05": -0.416341,
            "disp_diff_median_10": -0.349537,
            "disp_diff_median_25": -0.366071,
            "disp_costs_runtime": 0.003714,
            "nbc_nn_nb_sd_ratio": 0.54603,
            "nbc_nn_nb_mean_ratio": 0.803735,
            "nbc_nn_nb_cor": 0.421748,
            "nbc_dist_ratio_coeff_var": 0.238179,
            "nbc_nb_fitness_cor": -0.641934,
            "nbc_costs_runtime": 0.029719,
            "pca_expl_var_cov_x": 1.0,
            "pca_expl_var_cor_x": 1.0,
            "pca_expl_var_cov_init": 0.5,
            "pca_expl_var_cor_init": 1.0,
            "pca_expl_var_PC1_cov_x": 0.237642,
            "pca_expl_var_PC1_cor_x": 0.237647,
            "pca_expl_var_PC1_cov_init": 0.860898,
            "pca_expl_var_PC1_cor_init": 0.207556,
            "pca_costs_runtime": 0.00651,
            "ic_h_max": 0.830648,
            "ic_eps_s": 1.326326,
            "ic_eps_max": 1.679675,
            "ic_eps_ratio": 0.585586,
            "ic_m0": 0.608871,
            "ic_costs_runtime": 1.853252
        },
        "time": 2.637651
    },
    "2008116855045800014": {
        "result": {
            "ela_distr_skewness": -1.044262,
            "ela_distr_kurtosis": 0.237145,
            "ela_distr_number_of_peaks": 1.0,
            "ela_distr_costs_runtime": 0.041984,
            "ela_level_mmce_lda_10": 0.1,
            "ela_level_mmce_qda_10": 0.104,
            "ela_level_lda_qda_10": 0.961538,
            "ela_level_mmce_lda_25": 0.252,
            "ela_level_mmce_qda_25": 0.262,
            "ela_level_lda_qda_25": 0.969231,
            "ela_level_mmce_lda_50": 0.444,
            "ela_level_mmce_qda_50": 0.368,
            "ela_level_lda_qda_50": 1.218638,
            "ela_level_costs_runtime": 0.14565,
            "ela_meta_lin_simple_adj_r2": 0.030301,
            "ela_meta_lin_simple_intercept": 574.621042,
            "ela_meta_lin_simple_coef_min": 0.133714,
            "ela_meta_lin_simple_coef_max": 0.938005,
            "ela_meta_lin_simple_coef_max_by_min": 6.598314,
            "ela_meta_lin_w_interact_adj_r2": 0.061263,
            "ela_meta_quad_simple_adj_r2": 0.199955,
            "ela_meta_quad_simple_cond": 4.448601,
            "ela_meta_quad_w_interact_adj_r2": 0.281214,
            "ela_meta_costs_runtime": 0.394728,
            "disp_ratio_mean_02": 0.870651,
            "disp_ratio_mean_05": 0.868798,
            "disp_ratio_mean_10": 0.871911,
            "disp_ratio_mean_25": 0.890557,
            "disp_ratio_median_02": 0.890529,
            "disp_ratio_median_05": 0.852032,
            "disp_ratio_median_10": 0.869804,
            "disp_ratio_median_25": 0.884357,
            "disp_diff_mean_02": -1.138406,
            "disp_diff_mean_05": -1.156058,
            "disp_diff_mean_10": -1.127369,
            "disp_diff_mean_25": -0.963618,
            "disp_diff_median_02": -0.969821,
            "disp_diff_median_05": -1.307983,
            "disp_diff_median_10": -1.153041,
            "disp_diff_median_25": -1.02513,
            "disp_costs_runtime": 0.003744,
            "nbc_nn_nb_sd_ratio": 0.613013,
            "nbc_nn_nb_mean_ratio": 0.81615,
            "nbc_nn_nb_cor": 0.445976,
            "nbc_dist_ratio_coeff_var": 0.228208,
            "nbc_nb_fitness_cor": -0.63295,
            "nbc_costs_runtime": 0.028326,
            "pca_expl_var_cov_x": 1.0,
            "pca_expl_var_cor_x": 1.0,
            "pca_expl_var_cov_init": 0.333333,
            "pca_expl_var_cor_init": 1.0,
            "pca_expl_var_PC1_cov_x": 0.237642,
            "pca_expl_var_PC1_cor_x": 0.237647,
            "pca_expl_var_PC1_cov_init": 0.877085,
            "pca_expl_var_PC1_cor_init": 0.212818,
            "pca_costs_runtime": 0.006575,
            "ic_h_max": 0.835272,
            "ic_eps_s": 1.346346,
            "ic_eps_max": 2.019786,
            "ic_eps_ratio": 0.635636,
            "ic_m0": 0.614919,
            "ic_costs_runtime": 1.823158
        },
        "time": 2.748734
    },
    "2069555189022143647": {
        "result": {
            "ela_distr_skewness": -2.17054,
            "ela_distr_kurtosis": 9.951675,
            "ela_distr_number_of_peaks": 3.0,
            "ela_distr_costs_runtime": 0.028039,
            "ela_level_mmce_lda_10": 0.1,
            "ela_level_mmce_qda_10": 0.112,
            "ela_level_lda_qda_10": 0.892857,
            "ela_level_mmce_lda_25": 0.253,
            "ela_level_mmce_qda_25": 0.264,
            "ela_level_lda_qda_25": 0.961538,
            "ela_level_mmce_lda_50": 0.432,
            "ela_level_mmce_qda_50": 0.369,
            "ela_level_lda_qda_50": 1.15736,
            "ela_level_costs_runtime": 0.232424,
            "ela_meta_lin_simple_adj_r2": 0.033716,
            "ela_meta_lin_simple_intercept": 119.963535,
            "ela_meta_lin_simple_coef_min": 0.008327,
            "ela_meta_lin_simple_coef_max": 0.264051,
            "ela_meta_lin_simple_coef_max_by_min": 32.60414,
            "ela_meta_lin_w_interact_adj_r2": 0.106688,
            "ela_meta_quad_simple_adj_r2": 0.152331,
            "ela_meta_quad_simple_cond": 9.736828,
            "ela_meta_quad_w_interact_adj_r2": 0.228838,
            "ela_meta_costs_runtime": 0.841992,
            "disp_ratio_mean_02": 0.908741,
            "disp_ratio_mean_05": 0.917688,
            "disp_ratio_mean_10": 0.924553,
            "disp_ratio_mean_25": 0.929709,
            "disp_ratio_median_02": 0.913544,
            "disp_ratio_median_05": 0.923892,
            "disp_ratio_median_10": 0.923767,
            "disp_ratio_median_25": 0.929719,
            "disp_diff_mean_02": -1.158097,
            "disp_diff_mean_05": -1.044519,
            "disp_diff_mean_10": -0.957176,
            "disp_diff_mean_25": -0.892028,
            "disp_diff_median_02": -1.099721,
            "disp_diff_median_05": -0.968212,
            "disp_diff_median_10": -0.968783,
            "disp_diff_median_25": -0.892711,
            "disp_costs_runtime": 0.010356,
            "nbc_nn_nb_sd_ratio": 0.748706,
            "nbc_nn_nb_mean_ratio": 0.902108,
            "nbc_nn_nb_cor": 0.53337,
            "nbc_dist_ratio_coeff_var": 0.14015,
            "nbc_nb_fitness_cor": -0.633901,
            "nbc_costs_runtime": 0.053183,
            "pca_expl_var_cov_x": 0.9,
            "pca_expl_var_cor_x": 0.9,
            "pca_expl_var_cov_init": 0.909091,
            "pca_expl_var_cor_init": 0.909091,
            "pca_expl_var_PC1_cov_x": 0.121242,
            "pca_expl_var_PC1_cor_x": 0.121243,
            "pca_expl_var_PC1_cov_init": 0.290674,
            "pca_expl_var_PC1_cor_init": 0.115719,
            "pca_costs_runtime": 0.00717,
            "ic_h_max": 0.8457,
            "ic_eps_s": 0.655656,
            "ic_eps_max": 0.334599,
            "ic_eps_ratio": -0.155155,
            "ic_m0": 0.628514,
            "ic_costs_runtime": 1.914356
        },
        "time": 3.797204
    },
    "792975943760284083": {
        "result": {
            "ela_distr_skewness": -1.975829,
            "ela_distr_kurtosis": 7.801877,
            "ela_distr_number_of_peaks": 3.5,
            "ela_distr_costs_runtime": 0.038342,
            "ela_level_mmce_lda_10": 0.1,
            "ela_level_mmce_qda_10": 0.108,
            "ela_level_lda_qda_10": 0.925926,
            "ela_level_mmce_lda_25": 0.252,
            "ela_level_mmce_qda_25": 0.266,
            "ela_level_lda_qda_25": 0.958213,
            "ela_level_mmce_lda_50": 0.453,
            "ela_level_mmce_qda_50": 0.364,
            "ela_level_lda_qda_50": 1.221461,
            "ela_level_costs_runtime": 0.229601,
            "ela_meta_lin_simple_adj_r2": 0.024049,
            "ela_meta_lin_simple_intercept": 77.404565,
            "ela_meta_lin_simple_coef_min": 0.015006,
            "ela_meta_lin_simple_coef_max": 0.26821,
            "ela_meta_lin_simple_coef_max_by_min": 17.251852,
            "ela_meta_lin_w_interact_adj_r2": 0.099562,
            "ela_meta_quad_simple_adj_r2": 0.141092,
            "ela_meta_quad_simple_cond": 7.318719,
            "ela_meta_quad_w_interact_adj_r2": 0.257399,
            "ela_meta_costs_runtime": 1.025976,
            "disp_ratio_mean_02": 0.922969,
            "disp_ratio_mean_05": 0.920813,
            "disp_ratio_mean_10": 0.92783,
            "disp_ratio_mean_25": 0.931636,
            "disp_ratio_median_02": 0.93112,
            "disp_ratio_median_05": 0.9267,
            "disp_ratio_median_10": 0.930426,
            "disp_ratio_median_25": 0.930715,
            "disp_diff_mean_02": -0.97749,
            "disp_diff_mean_05": -1.004887,
            "disp_diff_mean_10": -0.915974,
            "disp_diff_mean_25": -0.867279,
            "disp_diff_median_02": -0.875881,
            "disp_diff_median_05": -0.932451,
            "disp_diff_median_10": -0.884881,
            "disp_diff_median_25": -0.880877,
            "disp_costs_runtime": 0.01082,
            "nbc_nn_nb_sd_ratio": 0.743641,
            "nbc_nn_nb_mean_ratio": 0.902283,
            "nbc_nn_nb_cor": 0.52827,
            "nbc_dist_ratio_coeff_var": 0.139949,
            "nbc_nb_fitness_cor": -0.638931,
            "nbc_costs_runtime": 0.053975,
            "pca_expl_var_cov_x": 0.9,
            "pca_expl_var_cor_x": 0.9,
            "pca_expl_var_cov_init": 0.909091,
            "pca_expl_var_cor_init": 0.909091,
            "pca_expl_var_PC1_cov_x": 0.121242,
            "pca_expl_var_PC1_cor_x": 0.121243,
            "pca_expl_var_PC1_cov_init": 0.294814,
            "pca_expl_var_PC1_cor_init": 0.115714,
            "pca_costs_runtime": 0.007163,
            "ic_h_max": 0.84245,
            "ic_eps_s": 0.615616,
            "ic_eps_max": 0.350384,
            "ic_eps_ratio": -0.155155,
            "ic_m0": 0.628514,
            "ic_costs_runtime": 2.165636
        },
        "time": 4.454099
    },
    "342368948904518777": {
        "result": {
            "ela_distr_skewness": -2.069176,
            "ela_distr_kurtosis": 7.748484,
            "ela_distr_number_of_peaks": 4.0,
            "ela_distr_costs_runtime": 0.039492,
            "ela_level_mmce_lda_10": 0.1,
            "ela_level_mmce_qda_10": 0.108,
            "ela_level_lda_qda_10": 0.925926,
            "ela_level_mmce_lda_25": 0.251,
            "ela_level_mmce_qda_25": 0.262,
            "ela_level_lda_qda_25": 0.958189,
            "ela_level_mmce_lda_50": 0.466,
            "ela_level_mmce_qda_50": 0.379,
            "ela_level_lda_qda_50": 1.246635,
            "ela_level_costs_runtime": 0.161172,
            "ela_meta_lin_simple_adj_r2": 0.016876,
            "ela_meta_lin_simple_intercept": -292.316953,
            "ela_meta_lin_simple_coef_min": 0.0121,
            "ela_meta_lin_simple_coef_max": 0.24179,
            "ela_meta_lin_simple_coef_max_by_min": 17.038278,
            "ela_meta_lin_w_interact_adj_r2": 0.078374,
            "ela_meta_quad_simple_adj_r2": 0.179651,
            "ela_meta_quad_simple_cond": 3.796544,
            "ela_meta_quad_w_interact_adj_r2": 0.265745,
            "ela_meta_costs_runtime": 0.96479,
            "disp_ratio_mean_02": 0.867502,
            "disp_ratio_mean_05": 0.890165,
            "disp_ratio_mean_10": 0.90098,
            "disp_ratio_mean_25": 0.92349,
            "disp_ratio_median_02": 0.870206,
            "disp_ratio_median_05": 0.885061,
            "disp_ratio_median_10": 0.900152,
            "disp_ratio_median_25": 0.922238,
            "disp_diff_mean_02": -1.681487,
            "disp_diff_mean_05": -1.393226,
            "disp_diff_mean_10": -1.25649,
            "disp_diff_mean_25": -0.970357,
            "disp_diff_median_02": -1.65112,
            "disp_diff_median_05": -1.461584,
            "disp_diff_median_10": -1.268792,
            "disp_diff_median_25": -0.988783,
            "disp_costs_runtime": 0.010503,
            "nbc_nn_nb_sd_ratio": 0.773912,
            "nbc_nn_nb_mean_ratio": 0.906621,
            "nbc_nn_nb_cor": 0.550104,
            "nbc_dist_ratio_coeff_var": 0.135562,
            "nbc_nb_fitness_cor": -0.651678,
            "nbc_costs_runtime": 0.051858,
            "pca_expl_var_cov_x": 0.9,
            "pca_expl_var_cor_x": 0.9,
            "pca_expl_var_cov_init": 0.909091,
            "pca_expl_var_cor_init": 0.909091,
            "pca_expl_var_PC1_cov_x": 0.121242,
            "pca_expl_var_PC1_cor_x": 0.121243,
            "pca_expl_var_PC1_cov_init": 0.30661,
            "pca_expl_var_PC1_cor_init": 0.113393,
            "pca_costs_runtime": 0.007221,
            "ic_h_max": 0.846423,
            "ic_eps_s": 0.665666,
            "ic_eps_max": 0.350384,
            "ic_eps_ratio": -0.115115,
            "ic_m0": 0.629518,
            "ic_costs_runtime": 1.993977
        },
        "time": 3.957603
    },
    "418178799945208885": {
        "result": {
            "ela_distr_skewness": -2.431688,
            "ela_distr_kurtosis": 11.262524,
            "ela_distr_number_of_peaks": 4.0,
            "ela_distr_costs_runtime": 0.036482,
            "ela_level_mmce_lda_10": 0.1,
            "ela_level_mmce_qda_10": 0.11,
            "ela_level_lda_qda_10": 0.909091,
            "ela_level_mmce_lda_25": 0.258,
            "ela_level_mmce_qda_25": 0.258,
            "ela_level_lda_qda_25": 1.003788,
            "ela_level_mmce_lda_50": 0.404,
            "ela_level_mmce_qda_50": 0.354,
            "ela_level_lda_qda_50": 1.133918,
            "ela_level_costs_runtime": 0.180379,
            "ela_meta_lin_simple_adj_r2": 0.064271,
            "ela_meta_lin_simple_intercept": 46.34999,
            "ela_meta_lin_simple_coef_min": 0.013669,
            "ela_meta_lin_simple_coef_max": 0.372899,
            "ela_meta_lin_simple_coef_max_by_min": 27.044141,
            "ela_meta_lin_w_interact_adj_r2": 0.104508,
            "ela_meta_quad_simple_adj_r2": 0.203066,
            "ela_meta_quad_simple_cond": 6.137601,
            "ela_meta_quad_w_interact_adj_r2": 0.266271,
            "ela_meta_costs_runtime": 1.575398,
            "disp_ratio_mean_02": 0.882134,
            "disp_ratio_mean_05": 0.899668,
            "disp_ratio_mean_10": 0.907974,
            "disp_ratio_mean_25": 0.923669,
            "disp_ratio_median_02": 0.886756,
            "disp_ratio_median_05": 0.903315,
            "disp_ratio_median_10": 0.910467,
            "disp_ratio_median_25": 0.92398,
            "disp_diff_mean_02": -1.495556,
            "disp_diff_mean_05": -1.272807,
            "disp_diff_mean_10": -1.167374,
            "disp_diff_mean_25": -0.968499,
            "disp_diff_median_02": -1.441313,
            "disp_diff_median_05": -1.230573,
            "disp_diff_median_10": -1.13835,
            "disp_diff_median_25": -0.967566,
            "disp_costs_runtime": 0.01079,
            "nbc_nn_nb_sd_ratio": 0.774627,
            "nbc_nn_nb_mean_ratio": 0.90588,
            "nbc_nn_nb_cor": 0.547463,
            "nbc_dist_ratio_coeff_var": 0.135987,
            "nbc_nb_fitness_cor": -0.639958,
            "nbc_costs_runtime": 0.052688,
            "pca_expl_var_cov_x": 0.9,
            "pca_expl_var_cor_x": 0.9,
            "pca_expl_var_cov_init": 0.909091,
            "pca_expl_var_cor_init": 0.909091,
            "pca_expl_var_PC1_cov_x": 0.121242,
            "pca_expl_var_PC1_cor_x": 0.121243,
            "pca_expl_var_PC1_cov_init": 0.315582,
            "pca_expl_var_PC1_cor_init": 0.121974,
            "pca_costs_runtime": 0.007253,
            "ic_h_max": 0.839534,
            "ic_eps_s": 0.685686,
            "ic_eps_max": 0.350384,
            "ic_eps_ratio": -0.155155,
            "ic_m0": 0.625502,
            "ic_costs_runtime": 2.699394
        },
        "time": 5.225509
    },
    "1666587809654208856": {
        "result": {
            "ela_distr_skewness": -2.154257,
            "ela_distr_kurtosis": 8.663723,
            "ela_distr_number_of_peaks": 3.5,
            "ela_distr_costs_runtime": 0.037672,
            "ela_level_mmce_lda_10": 0.1,
            "ela_level_mmce_qda_10": 0.108,
            "ela_level_lda_qda_10": 0.925926,
            "ela_level_mmce_lda_25": 0.252,
            "ela_level_mmce_qda_25": 0.266,
            "ela_level_lda_qda_25": 0.954887,
            "ela_level_mmce_lda_50": 0.457,
            "ela_level_mmce_qda_50": 0.38,
            "ela_level_lda_qda_50": 1.222768,
            "ela_level_costs_runtime": 0.247777,
            "ela_meta_lin_simple_adj_r2": 0.021702,
            "ela_meta_lin_simple_intercept": 594.008875,
            "ela_meta_lin_simple_coef_min": 0.007592,
            "ela_meta_lin_simple_coef_max": 0.242734,
            "ela_meta_lin_simple_coef_max_by_min": 33.204771,
            "ela_meta_lin_w_interact_adj_r2": 0.068073,
            "ela_meta_quad_simple_adj_r2": 0.187793,
            "ela_meta_quad_simple_cond": 3.975562,
            "ela_meta_quad_w_interact_adj_r2": 0.262085,
            "ela_meta_costs_runtime": 1.457452,
            "disp_ratio_mean_02": 0.900851,
            "disp_ratio_mean_05": 0.89861,
            "disp_ratio_mean_10": 0.910342,
            "disp_ratio_mean_25": 0.917475,
            "disp_ratio_median_02": 0.892338,
            "disp_ratio_median_05": 0.903151,
            "disp_ratio_median_10": 0.908118,
            "disp_ratio_median_25": 0.917096,
            "disp_diff_mean_02": -1.258309,
            "disp_diff_mean_05": -1.28614,
            "disp_diff_mean_10": -1.137356,
            "disp_diff_mean_25": -1.047323,
            "disp_diff_median_02": -1.369727,
            "disp_diff_median_05": -1.231357,
            "disp_diff_median_10": -1.166758,
            "disp_diff_median_25": -1.055508,
            "disp_costs_runtime": 0.010472,
            "nbc_nn_nb_sd_ratio": 0.758591,
            "nbc_nn_nb_mean_ratio": 0.904904,
            "nbc_nn_nb_cor": 0.534353,
            "nbc_dist_ratio_coeff_var": 0.138252,
            "nbc_nb_fitness_cor": -0.645906,
            "nbc_costs_runtime": 0.053372,
            "pca_expl_var_cov_x": 0.9,
            "pca_expl_var_cor_x": 0.9,
            "pca_expl_var_cov_init": 0.909091,
            "pca_expl_var_cor_init": 0.909091,
            "pca_expl_var_PC1_cov_x": 0.121242,
            "pca_expl_var_PC1_cor_x": 0.121243,
            "pca_expl_var_PC1_cov_init": 0.303351,
            "pca_expl_var_PC1_cor_init": 0.114108,
            "pca_costs_runtime": 0.007268,
            "ic_h_max": 0.849113,
            "ic_eps_s": 0.645646,
            "ic_eps_max": 0.366914,
            "ic_eps_ratio": -0.155155,
            "ic_m0": 0.630522,
            "ic_costs_runtime": 2.470252
        },
        "time": 4.861952
    },
    "434474887185780340": {
        "result": {
            "ela_distr_skewness": -2.610989,
            "ela_distr_kurtosis": 9.932334,
            "ela_distr_number_of_peaks": 5.0,
            "ela_distr_costs_runtime": 0.03076,
            "ela_level_mmce_lda_10": 0.1,
            "ela_level_mmce_qda_10": 0.115,
            "ela_level_lda_qda_10": 0.869565,
            "ela_level_mmce_lda_25": 0.2525,
            "ela_level_mmce_qda_25": 0.265,
            "ela_level_lda_qda_25": 0.952907,
            "ela_level_mmce_lda_50": 0.4505,
            "ela_level_mmce_qda_50": 0.376,
            "ela_level_lda_qda_50": 1.196495,
            "ela_level_costs_runtime": 2.467327,
            "ela_meta_lin_simple_adj_r2": 0.026011,
            "ela_meta_lin_simple_intercept": 125.474737,
            "ela_meta_lin_simple_coef_min": 0.001093,
            "ela_meta_lin_simple_coef_max": 0.062811,
            "ela_meta_lin_simple_coef_max_by_min": 51.952484,
            "ela_meta_lin_w_interact_adj_r2": 0.091075,
            "ela_meta_quad_simple_adj_r2": 0.178674,
            "ela_meta_quad_simple_cond": 4.943756,
            "ela_meta_quad_w_interact_adj_r2": 0.238318,
            "ela_meta_costs_runtime": 6.227182,
            "disp_ratio_mean_02": 0.919073,
            "disp_ratio_mean_05": 0.921623,
            "disp_ratio_mean_10": 0.927216,
            "disp_ratio_mean_25": 0.938379,
            "disp_ratio_median_02": 0.920355,
            "disp_ratio_median_05": 0.921721,
            "disp_ratio_median_10": 0.926589,
            "disp_ratio_median_25": 0.938162,
            "disp_diff_mean_02": -1.464993,
            "disp_diff_mean_05": -1.418697,
            "disp_diff_mean_10": -1.317846,
            "disp_diff_mean_25": -1.115623,
            "disp_diff_median_02": -1.444012,
            "disp_diff_median_05": -1.418977,
            "disp_diff_median_10": -1.331166,
            "disp_diff_median_25": -1.120996,
            "disp_costs_runtime": 0.047897,
            "nbc_nn_nb_sd_ratio": 0.878617,
            "nbc_nn_nb_mean_ratio": 0.953754,
            "nbc_nn_nb_cor": 0.631828,
            "nbc_dist_ratio_coeff_var": 0.077039,
            "nbc_nb_fitness_cor": -0.618026,
            "nbc_costs_runtime": 0.155081,
            "pca_expl_var_cov_x": 0.9,
            "pca_expl_var_cor_x": 0.9,
            "pca_expl_var_cov_init": 0.857143,
            "pca_expl_var_cor_init": 0.904762,
            "pca_expl_var_PC1_cov_x": 0.062363,
            "pca_expl_var_PC1_cor_x": 0.062206,
            "pca_expl_var_PC1_cov_init": 0.061688,
            "pca_expl_var_PC1_cor_init": 0.061355,
            "pca_costs_runtime": 0.224526,
            "ic_h_max": 0.820247,
            "ic_eps_s": -0.075075,
            "ic_eps_max": 0.046096,
            "ic_eps_ratio": -0.975976,
            "ic_m0": 0.640782,
            "ic_costs_runtime": 25.798556
        },
        "time": 37.351139
    },
    "533919195132528755": {
        "result": {
            "ela_distr_skewness": -2.690869,
            "ela_distr_kurtosis": 10.603285,
            "ela_distr_number_of_peaks": 5.0,
            "ela_distr_costs_runtime": 0.031678,
            "ela_level_mmce_lda_10": 0.1,
            "ela_level_mmce_qda_10": 0.113,
            "ela_level_lda_qda_10": 0.884956,
            "ela_level_mmce_lda_25": 0.255,
            "ela_level_mmce_qda_25": 0.261,
            "ela_level_lda_qda_25": 0.977136,
            "ela_level_mmce_lda_50": 0.435,
            "ela_level_mmce_qda_50": 0.366,
            "ela_level_lda_qda_50": 1.192414,
            "ela_level_costs_runtime": 2.677237,
            "ela_meta_lin_simple_adj_r2": 0.037245,
            "ela_meta_lin_simple_intercept": 83.155641,
            "ela_meta_lin_simple_coef_min": 0.001725,
            "ela_meta_lin_simple_coef_max": 0.066249,
            "ela_meta_lin_simple_coef_max_by_min": 37.94399,
            "ela_meta_lin_w_interact_adj_r2": 0.113921,
            "ela_meta_quad_simple_adj_r2": 0.169766,
            "ela_meta_quad_simple_cond": 4.684443,
            "ela_meta_quad_w_interact_adj_r2": 0.234525,
            "ela_meta_costs_runtime": 4.732844,
            "disp_ratio_mean_02": 0.916771,
            "disp_ratio_mean_05": 0.920853,
            "disp_ratio_mean_10": 0.928896,
            "disp_ratio_mean_25": 0.941406,
            "disp_ratio_median_02": 0.920723,
            "disp_ratio_median_05": 0.92458,
            "disp_ratio_median_10": 0.928052,
            "disp_ratio_median_25": 0.941501,
            "disp_diff_mean_02": -1.506753,
            "disp_diff_mean_05": -1.432789,
            "disp_diff_mean_10": -1.287245,
            "disp_diff_mean_25": -1.060673,
            "disp_diff_median_02": -1.436477,
            "disp_diff_median_05": -1.367143,
            "disp_diff_median_10": -1.30443,
            "disp_diff_median_25": -1.060414,
            "disp_costs_runtime": 0.047186,
            "nbc_nn_nb_sd_ratio": 0.870874,
            "nbc_nn_nb_mean_ratio": 0.953106,
            "nbc_nn_nb_cor": 0.622751,
            "nbc_dist_ratio_coeff_var": 0.077553,
            "nbc_nb_fitness_cor": -0.611358,
            "nbc_costs_runtime": 0.156029,
            "pca_expl_var_cov_x": 0.9,
            "pca_expl_var_cor_x": 0.9,
            "pca_expl_var_cov_init": 0.857143,
            "pca_expl_var_cor_init": 0.904762,
            "pca_expl_var_PC1_cov_x": 0.062363,
            "pca_expl_var_PC1_cor_x": 0.062206,
            "pca_expl_var_PC1_cov_init": 0.061693,
            "pca_expl_var_PC1_cor_init": 0.06187,
            "pca_costs_runtime": 0.198298,
            "ic_h_max": 0.818487,
            "ic_eps_s": -0.075075,
            "ic_eps_max": 0.042036,
            "ic_eps_ratio": -0.995996,
            "ic_m0": 0.638778,
            "ic_costs_runtime": 26.750312
        },
        "time": 36.316247
    },
    "1416530283410693500": {
        "result": {
            "ela_distr_skewness": -2.382186,
            "ela_distr_kurtosis": 8.043232,
            "ela_distr_number_of_peaks": 4.0,
            "ela_distr_costs_runtime": 0.029703,
            "ela_level_mmce_lda_10": 0.1,
            "ela_level_mmce_qda_10": 0.113,
            "ela_level_lda_qda_10": 0.884956,
            "ela_level_mmce_lda_25": 0.257,
            "ela_level_mmce_qda_25": 0.255,
            "ela_level_lda_qda_25": 1.0,
            "ela_level_mmce_lda_50": 0.415,
            "ela_level_mmce_qda_50": 0.353,
            "ela_level_lda_qda_50": 1.18772,
            "ela_level_costs_runtime": 2.555485,
            "ela_meta_lin_simple_adj_r2": 0.051859,
            "ela_meta_lin_simple_intercept": -286.179478,
            "ela_meta_lin_simple_coef_min": 0.002712,
            "ela_meta_lin_simple_coef_max": 0.076481,
            "ela_meta_lin_simple_coef_max_by_min": 25.103512,
            "ela_meta_lin_w_interact_adj_r2": 0.133007,
            "ela_meta_quad_simple_adj_r2": 0.215665,
            "ela_meta_quad_simple_cond": 5.800485,
            "ela_meta_quad_w_interact_adj_r2": 0.294051,
            "ela_meta_costs_runtime": 4.165906,
            "disp_ratio_mean_02": 0.911345,
            "disp_ratio_mean_05": 0.914381,
            "disp_ratio_mean_10": 0.921958,
            "disp_ratio_mean_25": 0.93586,
            "disp_ratio_median_02": 0.911068,
            "disp_ratio_median_05": 0.916046,
            "disp_ratio_median_10": 0.922077,
            "disp_ratio_median_25": 0.935829,
            "disp_diff_mean_02": -1.605115,
            "disp_diff_mean_05": -1.550034,
            "disp_diff_mean_10": -1.412829,
            "disp_diff_mean_25": -1.161098,
            "disp_diff_median_02": -1.611814,
            "disp_diff_median_05": -1.522155,
            "disp_diff_median_10": -1.41256,
            "disp_diff_median_25": -1.163294,
            "disp_costs_runtime": 0.050109,
            "nbc_nn_nb_sd_ratio": 0.888678,
            "nbc_nn_nb_mean_ratio": 0.954562,
            "nbc_nn_nb_cor": 0.635096,
            "nbc_dist_ratio_coeff_var": 0.076821,
            "nbc_nb_fitness_cor": -0.618436,
            "nbc_costs_runtime": 0.155618,
            "pca_expl_var_cov_x": 0.9,
            "pca_expl_var_cor_x": 0.9,
            "pca_expl_var_cov_init": 0.857143,
            "pca_expl_var_cor_init": 0.904762,
            "pca_expl_var_PC1_cov_x": 0.062363,
            "pca_expl_var_PC1_cor_x": 0.062206,
            "pca_expl_var_PC1_cov_init": 0.061956,
            "pca_expl_var_PC1_cor_init": 0.063095,
            "pca_costs_runtime": 0.227661,
            "ic_h_max": 0.819363,
            "ic_eps_s": -0.075075,
            "ic_eps_max": 0.044019,
            "ic_eps_ratio": -0.975976,
            "ic_m0": 0.640782,
            "ic_costs_runtime": 27.776599
        },
        "time": 37.203653
    },
    "2298002918734169895": {
        "result": {
            "ela_distr_skewness": -2.537684,
            "ela_distr_kurtosis": 9.488236,
            "ela_distr_number_of_peaks": 4.0,
            "ela_distr_costs_runtime": 0.037248,
            "ela_level_mmce_lda_10": 0.1,
            "ela_level_mmce_qda_10": 0.1135,
            "ela_level_lda_qda_10": 0.886461,
            "ela_level_mmce_lda_25": 0.254,
            "ela_level_mmce_qda_25": 0.26,
            "ela_level_lda_qda_25": 0.978734,
            "ela_level_mmce_lda_50": 0.436,
            "ela_level_mmce_qda_50": 0.361,
            "ela_level_lda_qda_50": 1.201093,
            "ela_level_costs_runtime": 2.63782,
            "ela_meta_lin_simple_adj_r2": 0.029874,
            "ela_meta_lin_simple_intercept": 52.143767,
            "ela_meta_lin_simple_coef_min": 0.000951,
            "ela_meta_lin_simple_coef_max": 0.070284,
            "ela_meta_lin_simple_coef_max_by_min": 68.225474,
            "ela_meta_lin_w_interact_adj_r2": 0.123786,
            "ela_meta_quad_simple_adj_r2": 0.17968,
            "ela_meta_quad_simple_cond": 6.512871,
            "ela_meta_quad_w_interact_adj_r2": 0.232296,
            "ela_meta_costs_runtime": 3.991574,
            "disp_ratio_mean_02": 0.909135,
            "disp_ratio_mean_05": 0.920391,
            "disp_ratio_mean_10": 0.926516,
            "disp_ratio_mean_25": 0.939606,
            "disp_ratio_median_02": 0.91532,
            "disp_ratio_median_05": 0.920499,
            "disp_ratio_median_10": 0.927295,
            "disp_ratio_median_25": 0.939607,
            "disp_diff_mean_02": -1.645199,
            "disp_diff_mean_05": -1.441095,
            "disp_diff_mean_10": -1.330325,
            "disp_diff_mean_25": -1.093358,
            "disp_diff_median_02": -1.53459,
            "disp_diff_median_05": -1.440339,
            "disp_diff_median_10": -1.318214,
            "disp_diff_median_25": -1.094884,
            "disp_costs_runtime": 0.051646,
            "nbc_nn_nb_sd_ratio": 0.875611,
            "nbc_nn_nb_mean_ratio": 0.953208,
            "nbc_nn_nb_cor": 0.628609,
            "nbc_dist_ratio_coeff_var": 0.077523,
            "nbc_nb_fitness_cor": -0.619166,
            "nbc_costs_runtime": 0.156074,
            "pca_expl_var_cov_x": 0.9,
            "pca_expl_var_cor_x": 0.9,
            "pca_expl_var_cov_init": 0.857143,
            "pca_expl_var_cor_init": 0.904762,
            "pca_expl_var_PC1_cov_x": 0.062363,
            "pca_expl_var_PC1_cor_x": 0.062206,
            "pca_expl_var_PC1_cov_init": 0.061748,
            "pca_expl_var_PC1_cor_init": 0.061704,
            "pca_costs_runtime": 0.205133,
            "ic_h_max": 0.820798,
            "ic_eps_s": -0.075075,
            "ic_eps_max": 0.043028,
            "ic_eps_ratio": -0.985986,
            "ic_m0": 0.642285,
            "ic_costs_runtime": 27.741948
        },
        "time": 37.075707
    },
    "201267609565576708": {
        "result": {
            "ela_distr_skewness": -2.444382,
            "ela_distr_kurtosis": 8.595649,
            "ela_distr_number_of_peaks": 4.0,
            "ela_distr_costs_runtime": 0.035241,
            "ela_level_mmce_lda_10": 0.1,
            "ela_level_mmce_qda_10": 0.112,
            "ela_level_lda_qda_10": 0.892857,
            "ela_level_mmce_lda_25": 0.255,
            "ela_level_mmce_qda_25": 0.255,
            "ela_level_lda_qda_25": 1.001852,
            "ela_level_mmce_lda_50": 0.419,
            "ela_level_mmce_qda_50": 0.354,
            "ela_level_lda_qda_50": 1.177955,
            "ela_level_costs_runtime": 2.482736,
            "ela_meta_lin_simple_adj_r2": 0.052381,
            "ela_meta_lin_simple_intercept": 599.846389,
            "ela_meta_lin_simple_coef_min": 0.001299,
            "ela_meta_lin_simple_coef_max": 0.102903,
            "ela_meta_lin_simple_coef_max_by_min": 70.371408,
            "ela_meta_lin_w_interact_adj_r2": 0.138189,
            "ela_meta_quad_simple_adj_r2": 0.227046,
            "ela_meta_quad_simple_cond": 4.330109,
            "ela_meta_quad_w_interact_adj_r2": 0.305725,
            "ela_meta_costs_runtime": 4.25361,
            "disp_ratio_mean_02": 0.905071,
            "disp_ratio_mean_05": 0.909353,
            "disp_ratio_mean_10": 0.916627,
            "disp_ratio_mean_25": 0.933431,
            "disp_ratio_median_02": 0.907009,
            "disp_ratio_median_05": 0.912548,
            "disp_ratio_median_10": 0.916833,
            "disp_ratio_median_25": 0.933205,
            "disp_diff_mean_02": -1.718416,
            "disp_diff_mean_05": -1.640899,
            "disp_diff_mean_10": -1.50941,
            "disp_diff_mean_25": -1.205022,
            "disp_diff_median_02": -1.685583,
            "disp_diff_median_05": -1.584877,
            "disp_diff_median_10": -1.507352,
            "disp_diff_median_25": -1.211299,
            "disp_costs_runtime": 0.051558,
            "nbc_nn_nb_sd_ratio": 0.891675,
            "nbc_nn_nb_mean_ratio": 0.95516,
            "nbc_nn_nb_cor": 0.639925,
            "nbc_dist_ratio_coeff_var": 0.076118,
            "nbc_nb_fitness_cor": -0.621822,
            "nbc_costs_runtime": 0.154467,
            "pca_expl_var_cov_x": 0.9,
            "pca_expl_var_cor_x": 0.9,
            "pca_expl_var_cov_init": 0.857143,
            "pca_expl_var_cor_init": 0.904762,
            "pca_expl_var_PC1_cov_x": 0.062363,
            "pca_expl_var_PC1_cor_x": 0.062206,
            "pca_expl_var_PC1_cov_init": 0.061539,
            "pca_expl_var_PC1_cor_init": 0.063252,
            "pca_costs_runtime": 0.238708,
            "ic_h_max": 0.824245,
            "ic_eps_s": -0.055055,
            "ic_eps_max": 0.050548,
            "ic_eps_ratio": -0.935936,
            "ic_m0": 0.635271,
            "ic_costs_runtime": 26.334369
        },
        "time": 36.718911
    }
}